ogcmaps/__init__.py
ogcmaps/cli.py
ogcmaps/collections.py
ogcmaps/conformance.py
ogcmaps/landing.py
ogcmaps/maps.py
ogcmaps/styles.py
ogcmaps/utils/__init__.py
ogcmaps/utils/commands.py
ogcmaps/utils/components.py
ogcmaps/utils/urls.py
ogcmaps-0.1.1.dist-info/LICENSE
ogcmaps-0.1.1.dist-info/METADATA
ogcmaps-0.1.1.dist-info/WHEEL
ogcmaps-0.1.1.dist-info/entry_points.txt
ogcmaps-0.1.1.dist-info/top_level.txt
ogcmaps-0.1.1.dist-info/RECORD
