Metadata-Version: 2.1
Name: ogcmaps
Version: 0.1.1
Summary: Python client and wrapper for OGC Maps API
Home-page: https://github.com/52North/api-maps-client
Author: 52°North
Author-email: info@52north.org
Project-URL: Bug Tracker, https://github.com/52North/api-maps-client/issues
Classifier: Programming Language :: Python :: 3
Classifier: License :: OSI Approved :: MIT License
Classifier: Operating System :: OS Independent
Requires-Python: >=3.6
License-File: LICENSE
Requires-Dist: requests-cache
Requires-Dist: click
Requires-Dist: requests
